esa.cpython-39-darwin.so
esaxx_py-0.2.7.dist-info/RECORD
esaxx_py-0.2.7.dist-info/LICENSE
esaxx_py-0.2.7.dist-info/WHEEL
esaxx_py-0.2.7.dist-info/top_level.txt
esaxx_py-0.2.7.dist-info/METADATA
