Metadata-Version: 2.1
Name: esaxx-py
Version: 0.2.7
Summary: Python wrapper of esaxx
Home-page: https://github.com/yusuke1997/esaxx-py
Author: Yusuke Sakai
Author-email: github@yusuke1997.jp
Classifier: Programming Language :: Python :: 3
Classifier: License :: OSI Approved :: MIT License
Classifier: Operating System :: OS Independent
Requires-Python: >=3.7
License-File: LICENSE
Requires-Dist: cython
